pulsar_metrics/__init__.py
pulsar_metrics/analyzers/base.py
pulsar_metrics/exceptions.py
pulsar_metrics/metrics/base.py
pulsar_metrics/metrics/drift.py
pulsar_metrics/metrics/enums.py
pulsar_metrics/metrics/performance.py
pulsar_metrics/metrics/statistics.py
pulsar_metrics/metrics/utils.py
pulsar_metrics/utils.py
pulsar_metrics-0.1.3.dist-info/LICENSE
pulsar_metrics-0.1.3.dist-info/WHEEL
pulsar_metrics-0.1.3.dist-info/METADATA
pulsar_metrics-0.1.3.dist-info/RECORD
