Metadata-Version: 2.1
Name: pulsar-metrics
Version: 0.1.3
Summary: Pulsar-metrics is an open-source Python library for evaluating and monitoring data and concept drift with an extensive set of metrics. It also offers the possibility to use custom metrics defined by the user.
Home-page: https://github.com/Rocket-Science-Development/pulsar_metrics
License: MIT
Author: Adel Benlagra
Author-email: abenlagra@rocketscience.one
Requires-Python: >=3.9,<3.10
Classifier: License :: OSI Approved :: MIT License
Classifier: Programming Language :: Python :: 3
Classifier: Programming Language :: Python :: 3.9
Requires-Dist: DateTime (>=4.5,<5.0)
Requires-Dist: black (>=22.6.0,<23.0.0)
Requires-Dist: pandas (>=1.4.3,<2.0.0)
Requires-Dist: pydantic (>=1.9.1,<2.0.0)
Requires-Dist: scikit-learn (>=1.1.1,<2.0.0)
Requires-Dist: scipy (>=1.7,<2.0)
Requires-Dist: tqdm (>=4.64.1,<5.0.0)
